pytest_docker_service/__init__.py
pytest_docker_service/container.py
pytest_docker_service/plugin.py
pytest_docker_service-0.2.8.dist-info/LICENSE
pytest_docker_service-0.2.8.dist-info/METADATA
pytest_docker_service-0.2.8.dist-info/WHEEL
pytest_docker_service-0.2.8.dist-info/entry_points.txt
pytest_docker_service-0.2.8.dist-info/RECORD
