Metadata-Version: 2.1
Name: pytest-docker-service
Version: 0.2.8
Summary: pytest plugin to start docker container
Home-page: https://github.com/ClementDelgrange/pytest-docker-service
License: GNU GPL v3
Keywords: pytest,docker,devops,CI
Author: Clément Delgrange
Requires-Python: >=3.9.0,<4.0
Classifier: Development Status :: 3 - Alpha
Classifier: Framework :: Pytest
Classifier: Intended Audience :: Developers
Classifier: License :: OSI Approved :: GNU Affero General Public License v3
Classifier: License :: Other/Proprietary License
Classifier: Operating System :: OS Independent
Classifier: Programming Language :: Python :: 3
Classifier: Programming Language :: Python :: 3.9
Classifier: Programming Language :: Python :: 3.10
Classifier: Programming Language :: Python :: 3.11
Classifier: Programming Language :: Python :: 3.12
Classifier: Topic :: Software Development :: Testing
Requires-Dist: docker (>=6.0.0)
Requires-Dist: pytest (>=7.1.3)
Requires-Dist: tenacity (>=8.1.0)
Project-URL: Repository, https://github.com/ClementDelgrange/pytest-docker-service
